{"help": "https://data.gov.sg/api/3/action/help_show?name=datastore_search", "success": true, "result": {"resource_id": "a48068a9-74e3-4748-9ab3-220e2e939419", "fields": [{"type": "int4", "id": "_id"}, {"type": "numeric", "id": "year"}, {"type": "numeric", "id": "rnd_expenditure"}, {"type": "int8", "id": "_full_count"}, {"type": "float4", "id": "rank"}], "q": "jones", "records": [], "_links": {"start": "/api/action/datastore_search?q=jones&resource_id=a48068a9-74e3-4748-9ab3-220e2e939419", "next": "/api/action/datastore_search?q=jones&offset=100&resource_id=a48068a9-74e3-4748-9ab3-220e2e939419"}}}